pyopenlayersqt/__init__.py
pyopenlayersqt/features_table.py
pyopenlayersqt/layers.py
pyopenlayersqt/models.py
pyopenlayersqt/range_slider.py
pyopenlayersqt/widget.py
pyopenlayersqt/resources/map.html
pyopenlayersqt/resources/ol_bridge.js
pyopenlayersqt/resources/qwebchannel.js
pyopenlayersqt/vendor/ol/ol.css
pyopenlayersqt/vendor/ol/ol.js
pyopenlayersqt-0.5.0.dist-info/METADATA
pyopenlayersqt-0.5.0.dist-info/WHEEL
pyopenlayersqt-0.5.0.dist-info/top_level.txt
pyopenlayersqt-0.5.0.dist-info/RECORD
