Metadata-Version: 2.1
Name: pyopenlayersqt
Version: 0.5.0
Summary: OpenLayers + Qt (QWebEngine) mapping widget for Python
Author: Your Name
License: MIT
Project-URL: Homepage, https://github.com/crroush/pyopenlayersqt
Project-URL: Repository, https://github.com/crroush/pyopenlayersqt
Project-URL: Issues, https://github.com/crroush/pyopenlayersqt/issues
Keywords: openlayers,qt,qwebengine,mapping,geospatial,gis,pyside6
Classifier: Development Status :: 4 - Beta
Classifier: Intended Audience :: Developers
Classifier: Programming Language :: Python :: 3
Classifier: Programming Language :: Python :: 3.8
Classifier: Programming Language :: Python :: 3.9
Classifier: Programming Language :: Python :: 3.10
Classifier: Programming Language :: Python :: 3.11
Classifier: Programming Language :: Python :: 3.12
Classifier: Topic :: Scientific/Engineering :: GIS
Classifier: Topic :: Software Development :: Libraries :: Python Modules
Requires-Python: >=3.8
Requires-Dist: PySide6>=6.5
Requires-Dist: numpy>=1.23
Requires-Dist: pillow>=10.0
Requires-Dist: matplotlib>=3.7
